aitermis/__init__.py
aitermis/cli.py
aitermis/parser.py
aitermis/url.py
aitermis-1.2.4.dist-info/METADATA
aitermis-1.2.4.dist-info/WHEEL
aitermis-1.2.4.dist-info/entry_points.txt
aitermis-1.2.4.dist-info/top_level.txt
aitermis-1.2.4.dist-info/RECORD
