Metadata-Version: 2.1
Name: aitermis
Version: 1.2.4
Summary: An ai powered terminal assistant to help you find the command you need!
Home-page: https://github.com/raspberri05/aitermis
Author: Naya Singhania
Author-email: naya.singhania@gmail.com
License: MIT
Classifier: Programming Language :: Python :: 3
Classifier: License :: OSI Approved :: MIT License
